CNCPy/Converting.py
CNCPy/Exceptions.py
CNCPy/__init__.py
CNCPy/premades/__init__.py
CNCPy/premades/lattice.py
CNCPy/premades/shapes.py
CNCPy-1.0.3.dist-info/LICENSE
CNCPy-1.0.3.dist-info/METADATA
CNCPy-1.0.3.dist-info/WHEEL
CNCPy-1.0.3.dist-info/top_level.txt
CNCPy-1.0.3.dist-info/RECORD
