Metadata-Version: 2.1
Name: CNCPy
Version: 1.0.3
Summary: Python cursor for writing large amounts of CNC GCODE.
Author-email: Roan Rothrock <roan.rothrock@hotmail.com>
Project-URL: Homepage, https://github.com/R-Rothrock/CNCPy
Classifier: Programming Language :: Python :: 3
Classifier: Operating System :: OS Independent
Requires-Python: >=3.4
License-File: LICENSE
